LICENSE.txt
MANIFEST.in
README.rst
setup.py
django_laconicurls.egg-info/PKG-INFO
django_laconicurls.egg-info/SOURCES.txt
django_laconicurls.egg-info/dependency_links.txt
django_laconicurls.egg-info/top_level.txt
laconicurls/__init__.py
laconicurls/admin.py
laconicurls/models.py
laconicurls/obfuscation.py
laconicurls/runtests.py
laconicurls/tests.py
laconicurls/urls.py
laconicurls/views.py