Metadata-Version: 1.1
Name: django-laconicurls
Version: 0.1.1
Summary: A generic url shortner for content in a Django ORM
Home-page: https://github.com/robert-b-clarke/django-laconicurls
Author: Robert Clarke
Author-email: rob@redanorak.co.uk
License: BSD License
Platform: UNKNOWN
Classifier: Environment :: Web Environment
Classifier: Framework :: Django
Classifier: Intended Audience :: Developers
Classifier: License :: OSI Approved :: BSD License
Classifier: Operating System :: OS Independent
Classifier: Programming Language :: Python
Classifier: Topic :: Internet :: WWW/HTTP
Classifier: Topic :: Internet :: WWW/HTTP :: Dynamic Content
Classifier: Development Status :: 4 - Beta
